flask_modus.py
setup.py
Flask_Modus.egg-info/PKG-INFO
Flask_Modus.egg-info/SOURCES.txt
Flask_Modus.egg-info/dependency_links.txt
Flask_Modus.egg-info/not-zip-safe
Flask_Modus.egg-info/requires.txt
Flask_Modus.egg-info/top_level.txt